prdoc/__init__.py
prdoc/cli.py
prdoc/cli_flag_detector.py
prdoc/config.py
prdoc/diff_parser.py
prdoc/doc_locator.py
prdoc/doc_search.py
prdoc/env.py
prdoc/errors.py
prdoc/fallback_patch.py
prdoc/gh_client.py
prdoc/gh_commenter.py
prdoc/git_utils.py
prdoc/llm_client.py
prdoc/llm_limits.py
prdoc/logging.py
prdoc/patch_generator.py
prdoc/plugins/base.py
prdoc/plugins/chroma_index.py
prdoc/plugins/ts_symbol_map.py
prdoc/prompts.py
prdoc/py_symbol_map.py
prdoc/telemetry.py
prdocc-0.1.6.dist-info/LICENSE
prdocc-0.1.6.dist-info/METADATA
prdocc-0.1.6.dist-info/WHEEL
prdocc-0.1.6.dist-info/entry_points.txt
prdocc-0.1.6.dist-info/RECORD
