Metadata-Version: 2.1
Name: prdocc
Version: 0.1.6
Summary: CLI tool to sync documentation with code changes in a pull request
License: MIT
Author: Bethvour
Author-email: bethvourc@gmail.com
Requires-Python: >=3.9,<4.0
Classifier: License :: OSI Approved :: MIT License
Classifier: Programming Language :: Python :: 3
Classifier: Programming Language :: Python :: 3.9
Classifier: Programming Language :: Python :: 3.10
Classifier: Programming Language :: Python :: 3.11
Classifier: Programming Language :: Python :: 3.12
Requires-Dist: chromadb (>=1.0.17,<2.0.0)
Requires-Dist: jinja2 (>=3.1.6,<4.0.0)
Requires-Dist: libcst (>=1.8.2,<2.0.0)
Requires-Dist: onnxruntime (==1.19.2)
Requires-Dist: openai (>=1.100.2,<2.0.0)
Requires-Dist: pygithub (>=2.7.0,<3.0.0)
Requires-Dist: python-dotenv (>=1.1.1,<2.0.0)
Requires-Dist: rich (>=14.1.0,<15.0.0)
Requires-Dist: sentence-transformers (>=5.1.0,<6.0.0)
Requires-Dist: typer[all] (>=0.12.3,<0.13.0)
